invrs_gym/__init__.py
invrs_gym/py.typed
invrs_gym/challenges/__init__.py
invrs_gym/challenges/base.py
invrs_gym/challenges/bayer/__init__.py
invrs_gym/challenges/bayer/challenge.py
invrs_gym/challenges/bayer/component.py
invrs_gym/challenges/ceviche/__init__.py
invrs_gym/challenges/ceviche/challenge.py
invrs_gym/challenges/ceviche/defaults.py
invrs_gym/challenges/diffract/__init__.py
invrs_gym/challenges/diffract/common.py
invrs_gym/challenges/diffract/metagrating_challenge.py
invrs_gym/challenges/diffract/splitter_challenge.py
invrs_gym/challenges/extractor/__init__.py
invrs_gym/challenges/extractor/challenge.py
invrs_gym/challenges/extractor/component.py
invrs_gym/challenges/library/challenge.py
invrs_gym/challenges/library/component.py
invrs_gym/challenges/library/data/__init__.py
invrs_gym/challenges/library/data/nk_tio2.csv
invrs_gym/challenges/metalens/challenge.py
invrs_gym/challenges/metalens/component.py
invrs_gym/loss/__init__.py
invrs_gym/loss/transmission_loss.py
invrs_gym/utils/__init__.py
invrs_gym/utils/initializers.py
invrs_gym/utils/materials.py
invrs_gym/utils/metrics.py
invrs_gym/utils/transforms.py
invrs_gym-1.6.2.dist-info/licenses/LICENSE
invrs_gym-1.6.2.dist-info/METADATA
invrs_gym-1.6.2.dist-info/WHEEL
invrs_gym-1.6.2.dist-info/top_level.txt
invrs_gym-1.6.2.dist-info/RECORD
