Metadata-Version: 2.4
Name: invrs_gym
Version: 1.6.2
Summary: A collection of inverse design challenges
Author-email: "Martin F. Schubert" <mfschubert@gmail.com>
Maintainer-email: "Martin F. Schubert" <mfschubert@gmail.com>
License-Expression: MIT
Keywords: topology,optimization,jax,inverse design
Requires-Python: >=3.7
License-File: LICENSE
Requires-Dist: agjax
Requires-Dist: ceviche_challenges
Requires-Dist: fmmax>=1.4.0
Requires-Dist: jax
Requires-Dist: jaxlib
Requires-Dist: numpy
Requires-Dist: refractiveindex2
Requires-Dist: totypes
Provides-Extra: examples
Requires-Dist: invrs-opt; extra == "examples"
Requires-Dist: invrs-utils; extra == "examples"
Requires-Dist: scikit-image; extra == "examples"
Provides-Extra: docs
Requires-Dist: ccmaps; extra == "docs"
Requires-Dist: imageruler; extra == "docs"
Requires-Dist: invrs_gym[examples]; extra == "docs"
Requires-Dist: matplotlib; extra == "docs"
Requires-Dist: jupyter-book; extra == "docs"
Requires-Dist: sphinx-autodoc-typehints; extra == "docs"
Requires-Dist: sphinx-click; extra == "docs"
Provides-Extra: tests
Requires-Dist: optax; extra == "tests"
Requires-Dist: parameterized; extra == "tests"
Requires-Dist: pytest; extra == "tests"
Requires-Dist: pytest-cov; extra == "tests"
Requires-Dist: pytest-subtests; extra == "tests"
Provides-Extra: dev
Requires-Dist: bump-my-version; extra == "dev"
Requires-Dist: darglint; extra == "dev"
Requires-Dist: invrs_gym[docs,examples,tests]; extra == "dev"
Requires-Dist: mypy; extra == "dev"
Requires-Dist: pre-commit; extra == "dev"
Dynamic: license-file
